Metadata-Version: 1.0
Name: uwosh.northstar
Version: 0.4
Summary: Provide a better mechanism to create and manage workflows for Plone TTW.
Home-page: https://141.233.238.172/svn/plone/Projects/uwosh.northstar
Author: Nathan Van Gheem
Author-email: vangheem@gmail.com
License: GPL
Keywords: workflow uwosh plone manager ajax
Platform: UNKNOWN
Classifier: Framework :: Plone
Classifier: Programming Language :: Python
